{
  "_comment": "Maps normalized Understat player names → TM search name. Add entries when Understat and TM use different name forms.",

  "abduqodir khusanov":         "Abdukodir Khusanov",
  "naif aguerd":                "Nayef Aguerd",
  "kephren thuram":             "Khephren Thuram",
  "vitalii mykolenko":          "Vitaliy Mykolenko",
  "sepe elye wahi":             "Elye Wahi",
  "azz-eddine ounahi":          "Azzedine Ounahi",
  "alex balde":                 "Alejandro Balde",
  "hichem boudaoui":            "Hicham Boudaoui",
  "mohammed amoura":            "Mohamed Amoura",
  "kylian mbappe-lottin":       "Kylian Mbappe",
  "franck zambo":               "Andre-Frank Zambo Anguissa",
  "dayotchanculle upamecano":   "Dayot Upamecano",
  "rayan ait nouri":            "Rayan Ait-Nouri",
  "mathis cherki":              "Rayan Cherki",

  "jean-daniel akpa-akpro":     "Jean-Daniel Akpa-Akpro",
  "abdelkabir abqar":           "Abdel Abqar",
  "bote baku":                  "Ridle Baku",
  "hong hyun-seok":             "Hyun-Seok Hong",
  "jean negoce":                "Jean-Matteo Bahoya",
  "jean-phillipe krasso":       "Jean-Philippe Krasso",
  "joshua vagnoman":            "Josha Vagnoman",
  "kelvin adou":                "Kelvin Amian",
  "kevin omoruyi":              "Kevin Carlos",
  "kim min-jae":                "Min-jae Kim",
  "lee kang-in":                "Kang-in Lee",
  "marc-oliver kempf":          "Marc-Oliver Kempf",
  "marius louar":               "Marius Louer",
  "mbwana samatta":             "Ally Samatta",
  "mohamed ali-cho":            "Mohamed Ali-Cho",
  "mohamed meite":              "Kader Meite",
  "philipp mwene":              "Phillipp Mwene",
  "pierre ganiou":              "Ismaelo Ganiou",
  "yannick engelhardt":         "Yannik Engelhardt",
  "yeremi pino":                "Yeremy Pino",
  "youssef el-arabi":           "Youssef El-Arabi",

  "amad diallo traore":         "Amad Diallo"
}
